MANIFEST.in
README.rst
setup.py
pytest_tmreport/__init__.py
pytest_tmreport/plugin.py
pytest_tmreport.egg-info/PKG-INFO
pytest_tmreport.egg-info/SOURCES.txt
pytest_tmreport.egg-info/dependency_links.txt
pytest_tmreport.egg-info/entry_points.txt
pytest_tmreport.egg-info/requires.txt
pytest_tmreport.egg-info/top_level.txt
pytest_tmreport/reports/template.html