Metadata-Version: 1.2
Name: pytest-tmreport
Version: 1.3.7
Summary: this is a vue-element ui report for pytest
Home-page: https://pypi.org/project/pytest-tmreport/
Author: Kevin Kai
Author-email: zykzml7788@sina.com
License: MIT
Keywords: py.test pytest vue element html report
Platform: UNKNOWN
Classifier: Environment :: Web Environment
Classifier: Intended Audience :: Developers
Classifier: Operating System :: OS Independent
Classifier: Topic :: Text Processing :: Indexing
Classifier: Topic :: Utilities
Classifier: Topic :: Internet
Classifier: Topic :: Software Development :: Libraries :: Python Modules
Classifier: Programming Language :: Python
Classifier: Programming Language :: Python :: 3.5
Classifier: Programming Language :: Python :: 3.6
Classifier: Programming Language :: Python :: 3.7
Classifier: Programming Language :: Python :: 3.8
Requires-Python: >=3.6
